README.md
setup.py
sepmachine/__init__.py
sepmachine.egg-info/PKG-INFO
sepmachine.egg-info/SOURCES.txt
sepmachine.egg-info/dependency_links.txt
sepmachine.egg-info/requires.txt
sepmachine.egg-info/top_level.txt
sepmachine/capture/__init__.py
sepmachine/capture/adb.py
sepmachine/capture/base.py
sepmachine/capture/empty.py
sepmachine/capture/scrcpy.py
sepmachine/handler/__init__.py
sepmachine/handler/base.py
sepmachine/handler/keras.py
sepmachine/handler/normal.py
sepmachine/pipeline/__init__.py
sepmachine/pipeline/base.py