Metadata-Version: 1.2
Name: sepmachine
Version: 0.3.2
Summary: stagesepx + video capture = auto workflow
Home-page: https://github.com/williamfzc/sepmachine
Author: williamfzc
Author-email: fengzc@vip.qq.com
License: MIT
Platform: UNKNOWN
Classifier: License :: OSI Approved :: MIT License
Classifier: Programming Language :: Python
Classifier: Programming Language :: Python :: 3
Classifier: Programming Language :: Python :: 3.6
Classifier: Programming Language :: Python :: 3.7
Requires-Python: >=3.6,<3.8
